flask_deprecate/__init__.py
flask_deprecate/flask_deprecate.py
flask_deprecate-0.1.3.dist-info/DESCRIPTION.rst
flask_deprecate-0.1.3.dist-info/METADATA
flask_deprecate-0.1.3.dist-info/RECORD
flask_deprecate-0.1.3.dist-info/WHEEL
flask_deprecate-0.1.3.dist-info/metadata.json
flask_deprecate-0.1.3.dist-info/top_level.txt
