Metadata-Version: 2.0
Name: flask-deprecate
Version: 0.1.3
Summary: Easy decorators for deprecating flask views and blueprints
Home-page: https://github.com/timmartin19/flask-deprecate
Author: Tim Martin
Author-email: oss@timmartin.me
License: MIT license
Keywords: flask_deprecate
Platform: UNKNOWN
Classifier: Development Status :: 2 - Pre-Alpha
Classifier: Intended Audience :: Developers
Classifier: License :: OSI Approved :: MIT License
Classifier: Natural Language :: English
Classifier: Programming Language :: Python :: 2
Classifier: Programming Language :: Python :: 2.6
Classifier: Programming Language :: Python :: 2.7
Classifier: Programming Language :: Python :: 3
Classifier: Programming Language :: Python :: 3.3
Classifier: Programming Language :: Python :: 3.4
Classifier: Programming Language :: Python :: 3.5
Requires-Dist: flask
